kalabash_admin/__init__.py
kalabash_admin/app_settings.py
kalabash_admin/apps.py
kalabash_admin/factories.py
kalabash_admin/handlers.py
kalabash_admin/kalmonak_extension.py
kalabash_admin/lib.py
kalabash_admin/postfix_maps.py
kalabash_admin/signals.py
kalabash_admin/urls.py
kalabash_admin/forms/__init__.py
kalabash_admin/forms/account.py
kalabash_admin/forms/alias.py
kalabash_admin/forms/base.py
kalabash_admin/forms/domain.py
kalabash_admin/forms/export.py
kalabash_admin/forms/forward.py
kalabash_admin/forms/import_.py
kalabash_admin/locale/en/LC_MESSAGES/django.mo
kalabash_admin/locale/en/LC_MESSAGES/django.po
kalabash_admin/locale/en/LC_MESSAGES/djangojs.mo
kalabash_admin/locale/en/LC_MESSAGES/djangojs.po
kalabash_admin/locale/fr/LC_MESSAGES/django.mo
kalabash_admin/locale/fr/LC_MESSAGES/django.po
kalabash_admin/locale/fr/LC_MESSAGES/djangojs.mo
kalabash_admin/locale/fr/LC_MESSAGES/djangojs.po
kalabash_admin/management/__init__.py
kalabash_admin/management/commands/__init__.py
kalabash_admin/management/commands/_import.py
kalabash_admin/management/commands/export_domains.py
kalabash_admin/management/commands/export_identities.py
kalabash_admin/management/commands/handle_mailbox_operations.py
kalabash_admin/management/commands/import_domains.py
kalabash_admin/management/commands/import_identities.py
kalabash_admin/migrations/0001_initial.py
kalabash_admin/migrations/0002_rename_content_types.py
kalabash_admin/migrations/0003_domain_type.py
kalabash_admin/migrations/0004_aliasrecipient.py
kalabash_admin/migrations/0005_set_full_address.py
kalabash_admin/migrations/0006_auto_20150729_1329.py
kalabash_admin/migrations/0007_auto_20150801_2101.py
kalabash_admin/migrations/0008_auto_20150928_2105.py
kalabash_admin/migrations/__init__.py
kalabash_admin/models/__init__.py
kalabash_admin/models/alias.py
kalabash_admin/models/base.py
kalabash_admin/models/domain.py
kalabash_admin/models/domain_alias.py
kalabash_admin/models/mailbox.py
kalabash_admin-1.1.4.dist-info/LICENSE
kalabash_admin-1.1.4.dist-info/METADATA
kalabash_admin-1.1.4.dist-info/WHEEL
kalabash_admin-1.1.4.dist-info/top_level.txt
kalabash_admin-1.1.4.dist-info/RECORD
